semcore_structuredlogger/__init__.py
semcore_structuredlogger/logger.py
semcore_structuredlogger-0.2.9.dist-info/WHEEL
semcore_structuredlogger-0.2.9.dist-info/entry_points.txt
semcore_structuredlogger-0.2.9.dist-info/METADATA
semcore_structuredlogger-0.2.9.dist-info/RECORD
