Metadata-Version: 2.4
Name: semcore-structuredlogger
Version: 0.2.9
Summary: A structured logger based on structlog
Author: imeakpan
Author-email: imeakpan <the.ime.akpan@gmail.com>
License-Expression: MIT
Classifier: Programming Language :: Python :: 3
Classifier: License :: OSI Approved :: MIT License
Classifier: Operating System :: OS Independent
Requires-Dist: structlog>=25.5.0
Requires-Python: >=3.10
